{"ygPerms":{"resourceCapabilityList":[{"resourceType":"GROUP","capabilities":[{"name":"READ"},{"name":"JOIN"}]},{"resourceType":"PHOTO","capabilities":[]},{"resourceType":"FILE","capabilities":[]},{"resourceType":"MEMBER","capabilities":[]},{"resourceType":"LINK","capabilities":[]},{"resourceType":"CALENDAR","capabilities":[]},{"resourceType":"DATABASE","capabilities":[]},{"resourceType":"POLL","capabilities":[]},{"resourceType":"MESSAGE","capabilities":[{"name":"READ"}]},{"resourceType":"PENDING_MESSAGE","capabilities":[]},{"resourceType":"ATTACHMENTS","capabilities":[{"name":"READ"}]},{"resourceType":"PHOTOMATIC_ALBUMS","capabilities":[]},{"resourceType":"MEMBERSHIP_TYPE","capabilities":[]},{"resourceType":"POST","capabilities":[{"name":"READ"}]},{"resourceType":"PIN","capabilities":[]}],"groupUrl":"groups.yahoo.com","intlCode":"us"},"comscore":"pageview_candidate","ygData":{"userId":152219847,"authorName":"cash_05","from":"&quot;cash_05&quot; &lt;cash_05@...&gt;","profile":"cash_05","replyTo":"LIST","senderId":"dSdFKFHYR6nYwdrKZjhL9B6YaK7FZ3qk6iSYqQSo7lncx9IJEnKvsRZi1Q8lQRIHL_yd06H3-TrctEpky-6N7n_e4wU","spamInfo":{"isSpam":false,"reason":"12"},"subject":"Re: Help! What always NOTCRAWLED","postDate":"1114936467","msgId":1773,"canDelete":false,"contentTrasformed":false,"systemMessage":false,"headers":{"messageIdInHeader":"PGQ1MjRhaiszZWc1QGVHcm91cHMuY29tPg==","inReplyToHeader":"PDQyNzFDRTBELjEwNzAxMDZAYXJjaGl2ZS5vcmc+"},"prevInTopic":1771,"nextInTopic":1775,"prevInTime":1772,"nextInTime":1774,"topicId":1760,"numMessagesInTopic":10,"msgSnippet":"Dear Gordan, After input the proxy address and port using expert setting, the crawler seeems to work a bit better. I enter a few seeds for testing, but only","rawEmail":"Return-Path: &lt;cash_05@...&gt;\r\nX-Sender: cash_05@...\r\nX-Apparently-To: archive-crawler@yahoogroups.com\r\nReceived: (qmail 7438 invoked from network); 1 May 2005 08:34:29 -0000\r\nReceived: from unknown (66.218.66.172)\n  by m26.grp.scd.yahoo.com with QMQP; 1 May 2005 08:34:29 -0000\r\nReceived: from unknown (HELO n27.bulk.scd.yahoo.com) (66.94.237.56)\n  by mta4.grp.scd.yahoo.com with SMTP; 1 May 2005 08:34:29 -0000\r\nReceived: from [66.218.69.6] by n27.bulk.scd.yahoo.com with NNFMP; 01 May 2005 08:34:29 -0000\r\nReceived: from [66.218.66.87] by mailer6.bulk.scd.yahoo.com with NNFMP; 01 May 2005 08:34:29 -0000\r\nDate: Sun, 01 May 2005 08:34:27 -0000\r\nTo: archive-crawler@yahoogroups.com\r\nMessage-ID: &lt;d524aj+3eg5@...&gt;\r\nIn-Reply-To: &lt;4271CE0D.1070106@...&gt;\r\nUser-Agent: eGroups-EW/0.82\r\nMIME-Version: 1.0\r\nContent-Type: text/plain; charset=ISO-8859-1\r\nContent-Length: 1034\r\nX-Mailer: Yahoo Groups Message Poster\r\nX-Yahoo-Newman-Property: groups-compose\r\nX-eGroups-Msg-Info: 1:12:0\r\nFrom: &quot;cash_05&quot; &lt;cash_05@...&gt;\r\nSubject: Re: Help! What always NOTCRAWLED\r\nX-Yahoo-Group-Post: member; u=152219847\r\nX-Yahoo-Profile: cash_05\r\n\r\nDear Gordan,\n\nAfter input the proxy address and port using expert setting, the\ncrawler seeems to work a bit better.\n\nI enter a few seeds for testing, but only one that is working. Details\nas below\n\nhttp://www.exploratorium.edu/  \t  Heritrix(-3)-Connection lost   \t\nFailed to crawl seed\n\nI can access to this site, however, there is a robots.txt on it. The\nrest all show failed to crawl seed except the last seed.\n\nhttp://www.arts.gov/ \t Heritrix(-61)-Robots prerequisite failure  \nFailed to crawl seed\n\nI can access this site via browser, and there is no\nhttp://www.arts.gov/robots.txt\n\nhttp://www.bagan.net.mm/ \t Heritrix(-61)-Robots prerequisite failure\n \tFailed to crawl seed\nSame, i can access this via browser and there is no\nhttp://www.bagan.net.mm/robots.txt\n\nThere a few more seeds with similar problems.\n\nhttp://www.sony.com/ \t HTTP-200-Success-OK  \tSeed successfully crawled\n\nThe crawler still running, it downloaded 9xxMB document. But i dont\nunderstand why only sony is ok while the rest all failed.\n\nAny help? Thank you.\n\n\n\n\n"}}