{"ygPerms":{"resourceCapabilityList":[{"resourceType":"GROUP","capabilities":[{"name":"READ"},{"name":"JOIN"}]},{"resourceType":"PHOTO","capabilities":[]},{"resourceType":"FILE","capabilities":[]},{"resourceType":"MEMBER","capabilities":[]},{"resourceType":"LINK","capabilities":[]},{"resourceType":"CALENDAR","capabilities":[]},{"resourceType":"DATABASE","capabilities":[]},{"resourceType":"POLL","capabilities":[]},{"resourceType":"MESSAGE","capabilities":[{"name":"READ"}]},{"resourceType":"PENDING_MESSAGE","capabilities":[]},{"resourceType":"ATTACHMENTS","capabilities":[{"name":"READ"}]},{"resourceType":"PHOTOMATIC_ALBUMS","capabilities":[]},{"resourceType":"MEMBERSHIP_TYPE","capabilities":[]},{"resourceType":"POST","capabilities":[{"name":"READ"}]},{"resourceType":"PIN","capabilities":[]}],"groupUrl":"groups.yahoo.com","intlCode":"us"},"comscore":"pageview_candidate","ygData":{"userId":168599281,"authorName":"Michael Stack","from":"Michael Stack &lt;stack@...&gt;","profile":"stackarchiveorg","replyTo":"LIST","senderId":"x6fmjZVSr6WnRhCLSMSkG604Bml8S2PG3d_P-99pQgXPOuy55GJmU0srdg94_PYpcheNCQkJ_BMhB-UxTyF_LjrgqnskGpWz","spamInfo":{"isSpam":false,"reason":"0"},"subject":"Re: [archive-crawler] Re: Heretrix Url Discovery","postDate":"1168042056","msgId":3671,"canDelete":false,"contentTrasformed":false,"systemMessage":false,"headers":{"messageIdInHeader":"PDQ1OUVFODQ4LjMwNDA5MDdAYXJjaGl2ZS5vcmc+","inReplyToHeader":"PGVubWZtYitic2g0QGVHcm91cHMuY29tPg==","referencesHeader":"PGVubWZtYitic2g0QGVHcm91cHMuY29tPg=="},"prevInTopic":3670,"nextInTopic":0,"prevInTime":3670,"nextInTime":3672,"topicId":3528,"numMessagesInTopic":9,"msgSnippet":"We re planning a 1.10.2 release in next week or two.  It will include the below addition. St.Ack","rawEmail":"Return-Path: &lt;stack@...&gt;\r\nX-Sender: stack@...\r\nX-Apparently-To: archive-crawler@yahoogroups.com\r\nReceived: (qmail 51469 invoked from network); 5 Jan 2007 23:59:15 -0000\r\nReceived: from unknown (66.218.66.172)\n  by m39.grp.scd.yahoo.com with QMQP; 5 Jan 2007 23:59:15 -0000\r\nReceived: from unknown (HELO mail.archive.org) (207.241.233.246)\n  by mta4.grp.scd.yahoo.com with SMTP; 5 Jan 2007 23:59:15 -0000\r\nReceived: from localhost (localhost [127.0.0.1])\n\tby mail.archive.org (Postfix) with ESMTP id 358B71416BF49;\n\tFri,  5 Jan 2007 15:58:40 -0800 (PST)\r\nReceived: from mail.archive.org ([127.0.0.1])\n\tby localhost (mail.archive.org [127.0.0.1]) (amavisd-new, port 10024)\n\twith LMTP id 23988-06-86; Fri, 5 Jan 2007 15:58:34 -0800 (PST)\r\nReceived: from [192.168.1.204] (c-71-198-60-165.hsd1.ca.comcast.net [71.198.60.165])\n\tby mail.archive.org (Postfix) with ESMTP id 3450114166A17;\n\tFri,  5 Jan 2007 15:58:34 -0800 (PST)\r\nMessage-ID: &lt;459EE848.3040907@...&gt;\r\nDate: Fri, 05 Jan 2007 16:07:36 -0800\r\nUser-Agent: Thunderbird 1.5.0.8 (X11/20061117)\r\nMIME-Version: 1.0\r\nTo: archive-crawler@yahoogroups.com\r\nReferences: &lt;enmfmb+bsh4@...&gt;\r\nIn-Reply-To: &lt;enmfmb+bsh4@...&gt;\r\nContent-Type: text/plain; charset=ISO-8859-1; format=flowed\r\nContent-Transfer-Encoding: 7bit\r\nX-Virus-Scanned: Debian amavisd-new at archive.org\r\nX-eGroups-Msg-Info: 1:0:0:0\r\nFrom: Michael Stack &lt;stack@...&gt;\r\nSubject: Re: [archive-crawler] Re: Heretrix Url Discovery\r\nX-Yahoo-Group-Post: member; u=168599281; y=LyU-4WFtrhP2BU5m6_erAlsZgOZznHjvmCvmxUrsTXMnvDUoy-uCSB4_\r\nX-Yahoo-Profile: stackarchiveorg\r\n\r\nWe&#39;re planning a 1.10.2 release in next week or two.  It will include \nthe below addition.\nSt.Ack\n\n\nnt_bdr wrote:\n&gt;\n&gt; --- In archive-crawler@yahoogroups.com \n&gt; &lt;mailto:archive-crawler%40yahoogroups.com&gt;, Gordon Mohr &lt;gojomo@...&gt;\n&gt; wrote:\n&gt; &gt;\n&gt; &gt; nt_bdr wrote:\n&gt; &gt; &gt; Is the version of Heretrix that that has the option to turn off\n&gt; &gt; &gt; ExtractorHTML Javascript extraction available for download? If so\n&gt; can\n&gt; &gt; &gt; you please provide me the link?\n&gt; &gt;\n&gt; &gt; No official, tested release has yet been made including this\n&gt; feature.\n&gt; &gt;\n&gt; &gt; Automatic builds from the CVS HEAD -- the latest code under source\n&gt; &gt; control -- are available from the continuous build box, at:\n&gt; &gt;\n&gt; &gt; http://builds.archive.org:8080/cruisecontrol/ \n&gt; &lt;http://builds.archive.org:8080/cruisecontrol/&gt;\n&gt; &gt;\n&gt; &gt; Look for &#39;HEAD-Heritrix&#39; then &#39;Build artifacts&#39;.\n&gt; &gt;\n&gt; &gt; Keep in mind that such builds are &#39;bleeding edge&#39; and may contain\n&gt; &gt; not-yet-documented changes, new bugs, and other issues.\n&gt; &gt;\n&gt; &gt; - Gordon @ IA\n&gt; &gt;\n&gt;\n&gt; Is there a Timeframe on when there will be an official release that\n&gt; will include the option to turn off the ExtractorHTML Javascript\n&gt; extraction?\n&gt;\n&gt;  \n\n\n"}}