{"ygPerms":{"resourceCapabilityList":[{"resourceType":"GROUP","capabilities":[{"name":"READ"},{"name":"JOIN"}]},{"resourceType":"PHOTO","capabilities":[]},{"resourceType":"FILE","capabilities":[]},{"resourceType":"MEMBER","capabilities":[]},{"resourceType":"LINK","capabilities":[]},{"resourceType":"CALENDAR","capabilities":[]},{"resourceType":"DATABASE","capabilities":[]},{"resourceType":"POLL","capabilities":[]},{"resourceType":"MESSAGE","capabilities":[{"name":"READ"}]},{"resourceType":"PENDING_MESSAGE","capabilities":[]},{"resourceType":"ATTACHMENTS","capabilities":[{"name":"READ"}]},{"resourceType":"PHOTOMATIC_ALBUMS","capabilities":[]},{"resourceType":"MEMBERSHIP_TYPE","capabilities":[]},{"resourceType":"POST","capabilities":[{"name":"READ"}]},{"resourceType":"PIN","capabilities":[]}],"groupUrl":"groups.yahoo.com","intlCode":"us"},"comscore":"pageview_candidate","ygData":{"userId":304578269,"authorName":"Someone","from":"Someone &lt;gohn_ban_5@...&gt;","profile":"gohn_ban_5","replyTo":"LIST","senderId":"zEaZiQP2PGCB91hNY4MoBYnCN8CuMP56Uaq9DbPLa78PymR-etk6KStaNzysHO1ZZEETeZrH8r6TNgFVEqTZLvcauaVd","spamInfo":{"isSpam":false,"reason":"3"},"subject":"Earn $0.50 per referral","postDate":"1179441569","msgId":4254,"canDelete":false,"contentTrasformed":false,"systemMessage":false,"headers":{},"prevInTopic":0,"nextInTopic":0,"prevInTime":4253,"nextInTime":4255,"topicId":4254,"numMessagesInTopic":1,"msgSnippet":"Affiliate Program Benefits : 1- Free Membership 2- Monthly Payments. 3- $25 Minimum Payouts. 4- Paypal and e-Gold Payouts. Join Now  :","rawEmail":"Return-Path: &lt;tqcrrhuitv@...&gt;\r\nX-Sender: tqcrrhuitv@...\r\nX-Apparently-To: archive-crawler@yahoogroups.com\r\nReceived: (qmail 95207 invoked from network); 17 May 2007 21:39:29 -0000\r\nReceived: from unknown (66.218.66.72)\n  by m44.grp.scd.yahoo.com with QMQP; 17 May 2007 21:39:29 -0000\r\nReceived: from unknown (HELO microsoft.com) (196.202.66.224)\n  by mta14.grp.scd.yahoo.com with SMTP; 17 May 2007 21:39:27 -0000\r\nTo: archive-crawler &lt;archive-crawler@yahoogroups.com&gt;\r\nX-Priority: 3\r\nX-MSMail-Priority: Normal\r\nmime-version: 1.0\r\ncontent-type: multipart/mixed;\n\tboundary=&quot;qzsoft_directmail_seperator&quot;\r\nX-eGroups-Msg-Info: 2:3:4:0\r\nFrom: Someone &lt;gohn_ban_5@...&gt;\r\nReply-To: Someone &lt;gohn_ban_5@...&gt;\r\nSubject: Earn $0.50 per referral\r\nX-Yahoo-Group-Post: member; u=304578269; y=tocg7ho47Cwagt83n3dRCZiSxmNQQccyx5FJM7Vd0AL1GjdUng\r\nX-Yahoo-Profile: gohn_ban_5\r\n\r\n\r\n--qzsoft_directmail_seperator\r\nContent-Type: text/plain;\n\tcharset=&quot;DEFAULT&quot;\r\nContent-Transfer-Encoding: base64\r\n\r\nQWZmaWxpYXRlIFByb2dyYW0gQmVuZWZpdHMgOgoKMS0gRnJlZSBNZW1iZXJzaGlwCgoyLSBNb250\r\naGx5IFBheW1lbnRzLgoKMy0gJDI1IE1pbmltdW0gUGF5b3V0cy4KCjQtIFBheXBhbCBhbmQgZS1H\r\nb2xkIFBheW91dHMuCgpKb2luIE5vdyAgOiBodHRwOi8vd3d3LmVhc3lsbmsuY29tLz9yZWZpZD0x\r\nMDAxCgpHb29kIEx1Y2s=\r\n\r\n\r\n--qzsoft_directmail_seperator--\r\n\n"}}