{"ygPerms":{"resourceCapabilityList":[{"resourceType":"GROUP","capabilities":[{"name":"READ"},{"name":"JOIN"}]},{"resourceType":"PHOTO","capabilities":[]},{"resourceType":"FILE","capabilities":[]},{"resourceType":"MEMBER","capabilities":[]},{"resourceType":"LINK","capabilities":[]},{"resourceType":"CALENDAR","capabilities":[]},{"resourceType":"DATABASE","capabilities":[]},{"resourceType":"POLL","capabilities":[]},{"resourceType":"MESSAGE","capabilities":[{"name":"READ"}]},{"resourceType":"PENDING_MESSAGE","capabilities":[]},{"resourceType":"ATTACHMENTS","capabilities":[{"name":"READ"}]},{"resourceType":"PHOTOMATIC_ALBUMS","capabilities":[]},{"resourceType":"MEMBERSHIP_TYPE","capabilities":[]},{"resourceType":"POST","capabilities":[{"name":"READ"}]},{"resourceType":"PIN","capabilities":[]}],"groupUrl":"groups.yahoo.com","intlCode":"us"},"comscore":"pageview_candidate","ygData":{"userId":127529970,"authorName":"Steven A Rowe","from":"Steven A Rowe &lt;sarowe@...&gt;","replyTo":"LIST","senderId":"wVmd7rMr91CtzIGBtj_e6XAJK30ht6SdxSWe000bG1vQRXNqg8DqxPx2NIRkNQ8ba_-jsKVScuFVTESFdHCh98ksE5Bi","spamInfo":{"isSpam":false,"reason":"12"},"subject":"Retry URIs with HTTP response code 500?","postDate":"1340778490","msgId":7717,"canDelete":false,"contentTrasformed":false,"systemMessage":false,"headers":{"messageIdInHeader":"PDZDNzhFOTdDNzA3QjVCNEM4Q0M2MUQ0NEY4NzU0NTg2MkI3MUY0QFNVRVgxMC1tYngtMDMuYWQuc3lyLmVkdT4="},"prevInTopic":0,"nextInTopic":7719,"prevInTime":7716,"nextInTime":7718,"topicId":7717,"numMessagesInTopic":2,"msgSnippet":"Hi, Using Heritrix 3.1, I d like a crawl to retry URIs that get HTTP access code 500 (Internal Server Error), but that doesn t seem to happen, and I can t","rawEmail":"Return-Path: &lt;sarowe@...&gt;\r\nX-Sender: sarowe@...\r\nX-Apparently-To: archive-crawler@yahoogroups.com\r\nX-Received: (qmail 16670 invoked from network); 27 Jun 2012 06:28:17 -0000\r\nX-Received: from unknown (98.137.35.162)\n  by m14.grp.sp2.yahoo.com with QMQP; 27 Jun 2012 06:28:17 -0000\r\nX-Received: from unknown (HELO smtp2.syr.edu) (128.230.18.92)\n  by mta6.grp.sp2.yahoo.com with SMTP; 27 Jun 2012 06:28:17 -0000\r\nX-Received: from suex10-hub-01.ad.syr.edu (suex10-hub-01.ad.syr.edu [128.230.108.124])\n\tby smtp2.syr.edu (8.14.5/8.14.5) with ESMTP id q5R6SBLZ019475\n\t(version=TLSv1/SSLv3 cipher=AES128-SHA bits=128 verify=FAIL)\n\tfor &lt;archive-crawler@yahoogroups.com&gt;; Wed, 27 Jun 2012 02:28:11 -0400\r\nX-Received: from SUEX10-MBX-03.ad.syr.edu ([128.230.108.186]) by\n suex10-hub-01.ad.syr.edu ([128.230.108.124]) with mapi id 14.02.0247.003;\n Wed, 27 Jun 2012 02:28:11 -0400\r\nTo: &quot;archive-crawler@yahoogroups.com&quot; &lt;archive-crawler@yahoogroups.com&gt;\r\nThread-Topic: Retry URIs with HTTP response code 500?\r\nThread-Index: Ac1ULgPv2C59gV2vQ8mFG645bYtvfQ==\r\nDate: Wed, 27 Jun 2012 06:28:10 +0000\r\nMessage-ID: &lt;6C78E97C707B5B4C8CC61D44F87545862B71F4@...&gt;\r\nAccept-Language: en-US\r\nContent-Language: en-US\r\nX-MS-Has-Attach:\r\nX-MS-TNEF-Correlator:\r\nContent-Type: text/plain; charset=&quot;us-ascii&quot;\r\nContent-Transfer-Encoding: quoted-printable\r\nMIME-Version: 1.0\r\nX-Proofpoint-Virus-Version: vendor=fsecure engine=2.50.10432:5.7.7855,1.0.260,0.0.0000\n definitions=2012-06-27_01:2012-06-27,2012-06-26,1970-01-01 signatures=0\r\nX-Proofpoint-Spam-Reason: safe\r\nX-eGroups-Msg-Info: 1:12:0:0:0\r\nFrom: Steven A Rowe &lt;sarowe@...&gt;\r\nSubject: Retry URIs with HTTP response code 500?\r\nX-Yahoo-Group-Post: member; u=127529970; y=ZwOkMQpaME-hNMP9yZZax_umTb4JslodRsfZq8tIFkhhY-hkEGoYCg\r\n\r\nHi,\n\nUsing Heritrix 3.1, I&#39;d like a crawl to retry URIs that get HTTP acces=\r\ns code 500 (Internal Server Error), but that doesn&#39;t seem to happen, and I =\r\ncan&#39;t figure out how to get Heritrix to do this.\n\nIs it possible to configu=\r\nre Heritrix to retry URIs with response code 500?\n\nSteve\n\n\n\n"}}